{
  "path": "packages/adapter-go/src/utils/go-utils.ts",
  "kind": "source",
  "purpose": "Discovers and validates Go and Delve debugger executables across platforms with version checking capabilities.",
  "topics": [
    "executable discovery",
    "cross-platform path resolution",
    "Go toolchain detection",
    "Delve debugger support",
    "version parsing",
    "DAP protocol validation",
    "environment variable handling"
  ],
  "public_surface": [
    "findGoExecutable",
    "findDelveExecutable",
    "getGoVersion",
    "getDelveVersion",
    "checkDelveDapSupport",
    "getGoSearchPaths"
  ]
}